airporttime/__init__.py
airporttime/ori_por_public.csv
tests/__init__.py
tests/test_airporttime.py
airporttime-0.0.0.dist-info/LICENSE
airporttime-0.0.0.dist-info/METADATA
airporttime-0.0.0.dist-info/WHEEL
airporttime-0.0.0.dist-info/top_level.txt
airporttime-0.0.0.dist-info/RECORD
