Metadata-Version: 2.1
Name: airporttime
Version: 0.0.0
Summary: convert local time to utc time by airport or vise-versa.
Home-page: https://github.com/liamcryan/airporttime
Author: Liam Cryan
Author-email: cryan.liam@gmail.com
License: UNKNOWN
Platform: UNKNOWN
Classifier: Programming Language :: Python :: 3
Requires-Dist: pytz
Requires-Dist: requests
